{
	"configurations" : 
	[
		{
			"directories" : 
			[
				{
					"build" : ".",
					"jsonFile" : "directory-.-Debug-d0094a50bb2071803777.json",
					"minimumCMakeVersion" : 
					{
						"string" : "3.27"
					},
					"projectIndex" : 0,
					"source" : ".",
					"targetIndexes" : 
					[
						0
					]
				}
			],
			"name" : "Debug",
			"projects" : 
			[
				{
					"directoryIndexes" : 
					[
						0
					],
					"name" : "F__Cooking_Time",
					"targetIndexes" : 
					[
						0
					]
				}
			],
			"targets" : 
			[
				{
					"directoryIndex" : 0,
					"id" : "F__Cooking_Time::@6890427a1f51a3e7e1df",
					"jsonFile" : "target-F__Cooking_Time-Debug-b4364e621a2a94a3821f.json",
					"name" : "F__Cooking_Time",
					"projectIndex" : 0
				}
			]
		}
	],
	"kind" : "codemodel",
	"paths" : 
	{
		"build" : "D:/CodeForces/F. Cooking Time/cmake-build-debug",
		"source" : "D:/CodeForces/F. Cooking Time"
	},
	"version" : 
	{
		"major" : 2,
		"minor" : 6
	}
}
